{
  "20000": {
    "seeds": [
      20003,
      20005,
      20016,
      20019,
      20022,
      20026,
      20039,
      20042,
      20047,
      20050,
      20051,
      20053,
      20056,
      20057,
      20059,
      20060,
      20061,
      20062,
      20067,
      20072,
      20075,
      20076,
      20077,
      20082,
      20086,
      20088,
      20092,
      20095,
      20096,
      20097,
      20100,
      20102,
      20103,
      20104,
      20108,
      20110,
      20114,
      20115,
      20118,
      20120,
      20121,
      20126,
      20129,
      20136,
      20140
    ],
    "episode_info": {
      "20000": [
        {
          "{A}": "020_hammer/base0",
          "{a}": "right"
        }
      ],
      "20001": [
        {
          "{A}": "020_hammer/base0",
          "{a}": "right"
        }
      ],
      "20002": [
        {
          "{A}": "020_hammer/base0",
          "{a}": "right"
        }
      ],
      "20003": [
        {
          "{A}": "020_hammer/base0",
          "{a}": "left"
        }
      ],
      "20004": [
        {
          "{A}": "020_hammer/base0",
          "{a}": "right"
        }
      ],
      "20005": [
        {
          "{A}": "020_hammer/base0",
          "{a}": "left"
        }
      ],
      "20008": [
        {
          "{A}": "020_hammer/base0",
          "{a}": "right"
        }
      ],
      "20011": [
        {
          "{A}": "020_hammer/base0",
          "{a}": "right"
        }
      ],
      "20014": [
        {
          "{A}": "020_hammer/base0",
          "{a}": "right"
        }
      ],
      "20015": [
        {
          "{A}": "020_hammer/base0",
          "{a}": "right"
        }
      ],
      "20016": [
        {
          "{A}": "020_hammer/base0",
          "{a}": "left"
        }
      ],
      "20017": [
        {
          "{A}": "020_hammer/base0",
          "{a}": "right"
        }
      ],
      "20018": [
        {
          "{A}": "020_hammer/base0",
          "{a}": "right"
        }
      ],
      "20019": [
        {
          "{A}": "020_hammer/base0",
          "{a}": "left"
        }
      ],
      "20020": [
        {
          "{A}": "020_hammer/base0",
          "{a}": "right"
        }
      ],
      "20021": [
        {
          "{A}": "020_hammer/base0",
          "{a}": "right"
        }
      ],
      "20022": [
        {
          "{A}": "020_hammer/base0",
          "{a}": "left"
        }
      ],
      "20023": [
        {
          "{A}": "020_hammer/base0",
          "{a}": "right"
        }
      ],
      "20026": [
        {
          "{A}": "020_hammer/base0",
          "{a}": "left"
        }
      ],
      "20028": [
        {
          "{A}": "020_hammer/base0",
          "{a}": "right"
        }
      ],
      "20029": [
        {
          "{A}": "020_hammer/base0",
          "{a}": "right"
        }
      ],
      "20032": [
        {
          "{A}": "020_hammer/base0",
          "{a}": "right"
        }
      ],
      "20033": [
        {
          "{A}": "020_hammer/base0",
          "{a}": "right"
        }
      ],
      "20034": [
        {
          "{A}": "020_hammer/base0",
          "{a}": "right"
        }
      ],
      "20035": [
        {
          "{A}": "020_hammer/base0",
          "{a}": "right"
        }
      ],
      "20038": [
        {
          "{A}": "020_hammer/base0",
          "{a}": "right"
        }
      ],
      "20039": [
        {
          "{A}": "020_hammer/base0",
          "{a}": "left"
        }
      ],
      "20040": [
        {
          "{A}": "020_hammer/base0",
          "{a}": "right"
        }
      ],
      "20041": [
        {
          "{A}": "020_hammer/base0",
          "{a}": "right"
        }
      ],
      "20042": [
        {
          "{A}": "020_hammer/base0",
          "{a}": "left"
        }
      ],
      "20043": [
        {
          "{A}": "020_hammer/base0",
          "{a}": "right"
        }
      ],
      "20044": [
        {
          "{A}": "020_hammer/base0",
          "{a}": "right"
        }
      ],
      "20045": [
        {
          "{A}": "020_hammer/base0",
          "{a}": "right"
        }
      ],
      "20047": [
        {
          "{A}": "020_hammer/base0",
          "{a}": "left"
        }
      ],
      "20048": [
        {
          "{A}": "020_hammer/base0",
          "{a}": "right"
        }
      ],
      "20050": [
        {
          "{A}": "020_hammer/base0",
          "{a}": "left"
        }
      ],
      "20051": [
        {
          "{A}": "020_hammer/base0",
          "{a}": "left"
        }
      ],
      "20053": [
        {
          "{A}": "020_hammer/base0",
          "{a}": "left"
        }
      ],
      "20054": [
        {
          "{A}": "020_hammer/base0",
          "{a}": "right"
        }
      ],
      "20056": [
        {
          "{A}": "020_hammer/base0",
          "{a}": "left"
        }
      ],
      "20057": [
        {
          "{A}": "020_hammer/base0",
          "{a}": "left"
        }
      ],
      "20058": [
        {
          "{A}": "020_hammer/base0",
          "{a}": "right"
        }
      ],
      "20059": [
        {
          "{A}": "020_hammer/base0",
          "{a}": "left"
        }
      ],
      "20060": [
        {
          "{A}": "020_hammer/base0",
          "{a}": "left"
        }
      ],
      "20061": [
        {
          "{A}": "020_hammer/base0",
          "{a}": "left"
        }
      ],
      "20062": [
        {
          "{A}": "020_hammer/base0",
          "{a}": "left"
        }
      ],
      "20064": [
        {
          "{A}": "020_hammer/base0",
          "{a}": "right"
        }
      ],
      "20065": [
        {
          "{A}": "020_hammer/base0",
          "{a}": "right"
        }
      ],
      "20067": [
        {
          "{A}": "020_hammer/base0",
          "{a}": "left"
        }
      ],
      "20068": [
        {
          "{A}": "020_hammer/base0",
          "{a}": "right"
        }
      ],
      "20072": [
        {
          "{A}": "020_hammer/base0",
          "{a}": "left"
        }
      ],
      "20074": [
        {
          "{A}": "020_hammer/base0",
          "{a}": "right"
        }
      ],
      "20075": [
        {
          "{A}": "020_hammer/base0",
          "{a}": "left"
        }
      ],
      "20076": [
        {
          "{A}": "020_hammer/base0",
          "{a}": "left"
        }
      ],
      "20077": [
        {
          "{A}": "020_hammer/base0",
          "{a}": "left"
        }
      ],
      "20078": [
        {
          "{A}": "020_hammer/base0",
          "{a}": "right"
        }
      ],
      "20081": [
        {
          "{A}": "020_hammer/base0",
          "{a}": "right"
        }
      ],
      "20082": [
        {
          "{A}": "020_hammer/base0",
          "{a}": "left"
        }
      ],
      "20086": [
        {
          "{A}": "020_hammer/base0",
          "{a}": "left"
        }
      ],
      "20087": [
        {
          "{A}": "020_hammer/base0",
          "{a}": "right"
        }
      ],
      "20088": [
        {
          "{A}": "020_hammer/base0",
          "{a}": "left"
        }
      ],
      "20089": [
        {
          "{A}": "020_hammer/base0",
          "{a}": "right"
        }
      ],
      "20091": [
        {
          "{A}": "020_hammer/base0",
          "{a}": "right"
        }
      ],
      "20092": [
        {
          "{A}": "020_hammer/base0",
          "{a}": "left"
        }
      ],
      "20094": [
        {
          "{A}": "020_hammer/base0",
          "{a}": "right"
        }
      ],
      "20095": [
        {
          "{A}": "020_hammer/base0",
          "{a}": "left"
        }
      ],
      "20096": [
        {
          "{A}": "020_hammer/base0",
          "{a}": "left"
        }
      ],
      "20097": [
        {
          "{A}": "020_hammer/base0",
          "{a}": "left"
        }
      ],
      "20098": [
        {
          "{A}": "020_hammer/base0",
          "{a}": "right"
        }
      ],
      "20100": [
        {
          "{A}": "020_hammer/base0",
          "{a}": "left"
        }
      ],
      "20102": [
        {
          "{A}": "020_hammer/base0",
          "{a}": "left"
        }
      ],
      "20103": [
        {
          "{A}": "020_hammer/base0",
          "{a}": "left"
        }
      ],
      "20104": [
        {
          "{A}": "020_hammer/base0",
          "{a}": "left"
        }
      ],
      "20105": [
        {
          "{A}": "020_hammer/base0",
          "{a}": "right"
        }
      ],
      "20108": [
        {
          "{A}": "020_hammer/base0",
          "{a}": "left"
        }
      ],
      "20110": [
        {
          "{A}": "020_hammer/base0",
          "{a}": "left"
        }
      ],
      "20112": [
        {
          "{A}": "020_hammer/base0",
          "{a}": "right"
        }
      ],
      "20113": [
        {
          "{A}": "020_hammer/base0",
          "{a}": "right"
        }
      ],
      "20114": [
        {
          "{A}": "020_hammer/base0",
          "{a}": "left"
        }
      ],
      "20115": [
        {
          "{A}": "020_hammer/base0",
          "{a}": "left"
        }
      ],
      "20118": [
        {
          "{A}": "020_hammer/base0",
          "{a}": "left"
        }
      ],
      "20120": [
        {
          "{A}": "020_hammer/base0",
          "{a}": "left"
        }
      ],
      "20121": [
        {
          "{A}": "020_hammer/base0",
          "{a}": "left"
        }
      ],
      "20122": [
        {
          "{A}": "020_hammer/base0",
          "{a}": "right"
        }
      ],
      "20123": [
        {
          "{A}": "020_hammer/base0",
          "{a}": "right"
        }
      ],
      "20124": [
        {
          "{A}": "020_hammer/base0",
          "{a}": "right"
        }
      ],
      "20125": [
        {
          "{A}": "020_hammer/base0",
          "{a}": "right"
        }
      ],
      "20126": [
        {
          "{A}": "020_hammer/base0",
          "{a}": "left"
        }
      ],
      "20127": [
        {
          "{A}": "020_hammer/base0",
          "{a}": "right"
        }
      ],
      "20128": [
        {
          "{A}": "020_hammer/base0",
          "{a}": "right"
        }
      ],
      "20129": [
        {
          "{A}": "020_hammer/base0",
          "{a}": "left"
        }
      ],
      "20132": [
        {
          "{A}": "020_hammer/base0",
          "{a}": "right"
        }
      ],
      "20134": [
        {
          "{A}": "020_hammer/base0",
          "{a}": "right"
        }
      ],
      "20135": [
        {
          "{A}": "020_hammer/base0",
          "{a}": "right"
        }
      ],
      "20136": [
        {
          "{A}": "020_hammer/base0",
          "{a}": "left"
        }
      ],
      "20137": [
        {
          "{A}": "020_hammer/base0",
          "{a}": "right"
        }
      ],
      "20138": [
        {
          "{A}": "020_hammer/base0",
          "{a}": "right"
        }
      ],
      "20140": [
        {
          "{A}": "020_hammer/base0",
          "{a}": "left"
        }
      ],
      "20141": [
        {
          "{A}": "020_hammer/base0",
          "{a}": "right"
        }
      ],
      "20142": [
        {
          "{A}": "020_hammer/base0",
          "{a}": "right"
        }
      ]
    }
  }
}